cache.py
docgen.py
main.py
model.py
cargo_aidoc-0.1.3.dist-info/licenses/LICENCE
cargo_aidoc-0.1.3.dist-info/METADATA
cargo_aidoc-0.1.3.dist-info/WHEEL
cargo_aidoc-0.1.3.dist-info/entry_points.txt
cargo_aidoc-0.1.3.dist-info/top_level.txt
cargo_aidoc-0.1.3.dist-info/RECORD
