Metadata-Version: 2.4
Name: cargo-aidoc
Version: 0.1.3
Summary: `cargo-aidoc` is a Python script that leverages Large Language Models (LLMs) to automatically generate documentation comments for Rust code items like functions, structs, enums, etc.
Requires-Python: ==3.11.12
License-File: LICENCE
Requires-Dist: click>=8.1.8
Requires-Dist: mirascope[openai]>=1.22.3
Requires-Dist: mirascope[anthropic]>=1.22.3
Requires-Dist: mirascope[google]>=1.22.3
Requires-Dist: mirascope[groq]>=1.22.3
Requires-Dist: mirascope[xai]>=1.22.3
Requires-Dist: mirascope[cohere]>=1.22.3
Requires-Dist: mirascope[litellm]>=1.22.3
Requires-Dist: mirascope[azure]>=1.22.3
Requires-Dist: mirascope[bedrock]>=1.22.3
Requires-Dist: termcolor>=3.0.1
Requires-Dist: toml>=0.10.2
Requires-Dist: tree-sitter==0.24.0
Requires-Dist: tree-sitter-rust==0.23.0
Dynamic: license-file
